setup.cfg
setup.py
langgen/__init__.py
langgen/langgen.py
langgen.egg-info/PKG-INFO
langgen.egg-info/SOURCES.txt
langgen.egg-info/dependency_links.txt
langgen.egg-info/requires.txt
langgen.egg-info/top_level.txt
test/test_namegen.py