Metadata-Version: 1.1
Name: langgen
Version: 0.1.2
Summary: Languages and names generator
Home-page: http://github.com/ftomassetti/langgen/
Author: Federico Tomassetti
Author-email: f.tomassetti@gmail.com
License: Apache Software License
Platform: any
Classifier: Programming Language :: Python
Classifier: Development Status :: 4 - Beta
Classifier: Natural Language :: English
Classifier: Intended Audience :: Developers
Classifier: License :: OSI Approved :: Apache Software License
Classifier: Operating System :: OS Independent
